Metadata-Version: 2.1
Name: nitvars
Version: 1.1
Summary: new versions of globals,locals,tracer and other functions..
Home-page: https://github.com/NITSoftware/nitvars
Author-email: createsoft@mail.ru
License: UNKNOWN
Platform: UNKNOWN
Classifier: Programming Language :: Python :: 3
Classifier: License :: OSI Approved :: MIT License
Classifier: Operating System :: OS Independent
Requires-Python: >=3.5
